nestlify/__init__.py
nestlify/nesting/__init__.py
nestlify/nesting/nester.py
nestlify/testing/__init__.py
nestlify/testing/nestor.py
nestlify_richard_arc-0.0.1.dist-info/DESCRIPTION.rst
nestlify_richard_arc-0.0.1.dist-info/METADATA
nestlify_richard_arc-0.0.1.dist-info/RECORD
nestlify_richard_arc-0.0.1.dist-info/WHEEL
nestlify_richard_arc-0.0.1.dist-info/metadata.json
nestlify_richard_arc-0.0.1.dist-info/top_level.txt
